xcom485i/__init__.py
xcom485i/addresses.py
xcom485i/client.py
xcom485i-0.9.3.dist-info/LICENSE
xcom485i-0.9.3.dist-info/METADATA
xcom485i-0.9.3.dist-info/WHEEL
xcom485i-0.9.3.dist-info/top_level.txt
xcom485i-0.9.3.dist-info/RECORD
